{
  "config": {
    "output_dir": "results\\mg_lafr_forecast",
    "length": 7000,
    "context_patches": 24,
    "horizon_patches": 4,
    "patch": 4,
    "stride_patches": 1,
    "epochs": 35,
    "batch_size": 128,
    "lr": 0.002,
    "seed": 13,
    "device": "cuda"
  },
  "device": "cuda",
  "train_windows": 1198,
  "test_windows": 522,
  "history": [
    {
      "epoch": 1,
      "train_mse": 0.9905520439147949,
      "train_mae": 0.8229254066944123
    },
    {
      "epoch": 2,
      "train_mse": 0.5700437366962433,
      "train_mae": 0.5837662070989609
    },
    {
      "epoch": 3,
      "train_mse": 0.3575572192668915,
      "train_mae": 0.45433181822299956
    },
    {
      "epoch": 4,
      "train_mse": 0.26450383067131045,
      "train_mae": 0.40254220068454744
    },
    {
      "epoch": 5,
      "train_mse": 0.2204224318265915,
      "train_mae": 0.3709210753440857
    },
    {
      "epoch": 6,
      "train_mse": 0.18027202486991883,
      "train_mae": 0.3385168731212616
    },
    {
      "epoch": 7,
      "train_mse": 0.17498203217983246,
      "train_mae": 0.33374758064746857
    },
    {
      "epoch": 8,
      "train_mse": 0.14357541128993034,
      "train_mae": 0.2942389279603958
    },
    {
      "epoch": 9,
      "train_mse": 0.10552742183208466,
      "train_mae": 0.2549455717206001
    },
    {
      "epoch": 10,
      "train_mse": 0.0905739851295948,
      "train_mae": 0.23570673316717147
    },
    {
      "epoch": 11,
      "train_mse": 0.09128782525658607,
      "train_mae": 0.23631056696176528
    },
    {
      "epoch": 12,
      "train_mse": 0.10732864364981651,
      "train_mae": 0.25417920351028445
    },
    {
      "epoch": 13,
      "train_mse": 0.09673605710268021,
      "train_mae": 0.24249629378318788
    },
    {
      "epoch": 14,
      "train_mse": 0.08102698773145675,
      "train_mae": 0.2265671044588089
    },
    {
      "epoch": 15,
      "train_mse": 0.07081431113183498,
      "train_mae": 0.21175584942102432
    },
    {
      "epoch": 16,
      "train_mse": 0.06153916120529175,
      "train_mae": 0.19520984292030336
    },
    {
      "epoch": 17,
      "train_mse": 0.06420827209949494,
      "train_mae": 0.20134674459695817
    },
    {
      "epoch": 18,
      "train_mse": 0.050353822857141496,
      "train_mae": 0.17798636853694916
    },
    {
      "epoch": 19,
      "train_mse": 0.04914549104869366,
      "train_mae": 0.17534783035516738
    },
    {
      "epoch": 20,
      "train_mse": 0.047317244857549665,
      "train_mae": 0.17116186022758484
    },
    {
      "epoch": 21,
      "train_mse": 0.04668717607855797,
      "train_mae": 0.17016831934452056
    },
    {
      "epoch": 22,
      "train_mse": 0.04236376844346523,
      "train_mae": 0.1595219627022743
    },
    {
      "epoch": 23,
      "train_mse": 0.037149524129927156,
      "train_mae": 0.14881696477532386
    },
    {
      "epoch": 24,
      "train_mse": 0.02557274978607893,
      "train_mae": 0.12432134449481964
    },
    {
      "epoch": 25,
      "train_mse": 0.02269783578813076,
      "train_mae": 0.11813107877969742
    },
    {
      "epoch": 26,
      "train_mse": 0.020930176600813866,
      "train_mae": 0.1144197091460228
    },
    {
      "epoch": 27,
      "train_mse": 0.019808976352214812,
      "train_mae": 0.10884247571229935
    },
    {
      "epoch": 28,
      "train_mse": 0.01859050840139389,
      "train_mae": 0.10732473731040955
    },
    {
      "epoch": 29,
      "train_mse": 0.018004402052611113,
      "train_mae": 0.10511182844638825
    },
    {
      "epoch": 30,
      "train_mse": 0.02251414703205228,
      "train_mae": 0.11406772956252098
    },
    {
      "epoch": 31,
      "train_mse": 0.015519084595143794,
      "train_mae": 0.09674898013472558
    },
    {
      "epoch": 32,
      "train_mse": 0.012599879875779152,
      "train_mae": 0.08726158738136292
    },
    {
      "epoch": 33,
      "train_mse": 0.01074555404484272,
      "train_mae": 0.0804410383105278
    },
    {
      "epoch": 34,
      "train_mse": 0.010471799969673156,
      "train_mae": 0.07920447885990142
    },
    {
      "epoch": 35,
      "train_mse": 0.013902208302170038,
      "train_mae": 0.09163940697908401
    }
  ],
  "lafr_main": {
    "mse": 0.017356734722852707,
    "mae": 0.0960550606250763,
    "rmse": 0.13174496090117718,
    "r2": 0.9818497514293746
  },
  "naive_main": {
    "mse": 1.4694544076919556,
    "mae": 0.9728997945785522,
    "rmse": 1.2122105459415684,
    "r2": -0.5366348099849598
  },
  "lafr_all_channels": {
    "mse": 0.01769484579563141,
    "mae": 0.09820596128702164,
    "rmse": 0.13302197485991332,
    "r2": 0.9814318724421311
  },
  "naive_all_channels": {
    "mse": 1.5096685886383057,
    "mae": 0.9877884984016418,
    "rmse": 1.2286857159739042,
    "r2": -0.5841742419063403
  }
}